azcam_fastapi/__init__.py
azcam_fastapi/fastapi_server.py
azcam_fastapi/test_send_json.py
azcam_fastapi-22.3.3.dist-info/LICENSE
azcam_fastapi-22.3.3.dist-info/WHEEL
azcam_fastapi-22.3.3.dist-info/METADATA
azcam_fastapi-22.3.3.dist-info/RECORD
