Metadata-Version: 2.1
Name: azcam-fastapi
Version: 22.3.3
Summary: Azcam-fastapi is an azcam extension which implements a fastapi-based webserver
Keywords: ccd,imaging,astronomy,sensors
Author: Michael Lesser
Author-email: mlesser@arizona.edu
Requires-Dist: azcam
Requires-Dist: fastapi
Requires-Dist: uvicorn
Requires-Dist: jinja2
Project-URL: Documentation, https://mplesser.github.io/azcam/
Project-URL: Repository, https://github.com/mplesser/azcam-fastapi/
